{
    "cityno": [
        {
            "province": "北京",
            "city": [
                {
                    "city_name": "北京",
                    "no": "101010100"
                },
                {
                    "city_name": "朝阳",
                    "no": "101010300"
                },
                {
                    "city_name": "顺义",
                    "no": "101010400"
                },
                {
                    "city_name": "怀柔",
                    "no": "101010500"
                },
                {
                    "city_name": "通州",
                    "no": "101010600"
                },
                {
                    "city_name": "昌平",
                    "no": "101010700"
                },
                {
                    "city_name": "延庆",
                    "no": "101010800"
                },
                {
                    "city_name": "丰台",
                    "no": "101010900"
                },
                {
                    "city_name": "石景山",
                    "no": "101011000"
                },
                {
                    "city_name": "大兴",
                    "no": "101011100"
                },
                {
                    "city_name": "房山",
                    "no": "101011200"
                },
                {
                    "city_name": "密云",
                    "no": "101011300"
                },
                {
                    "city_name": "门头沟",
                    "no": "101011400"
                },
                {
                    "city_name": "平谷",
                    "no": "101011500"
                },
                {
                    "city_name": "八达岭",
                    "no": "101011600"
                },
                {
                    "city_name": "佛爷顶",
                    "no": "101011700"
                },
                {
                    "city_name": "汤河口",
                    "no": "101011800"
                },
                {
                    "city_name": "密云上甸子",
                    "no": "101011900"
                },
                {
                    "city_name": "斋堂",
                    "no": "101012000"
                },
                {
                    "city_name": "霞云岭",
                    "no": "101012100"
                },
                {
                    "city_name": "北京城区",
                    "no": "101012200"
                },
                {
                    "city_name": "海淀",
                    "no": "101010200"
                }
            ]
        },
        {
            "province": "天津",
            "city": [
                {
                    "city_name": "天津",
                    "no": "101030100"
                },
                {
                    "city_name": "宝坻",
                    "no": "101030300"
                },
                {
                    "city_name": "东丽",
                    "no": "101030400"
                },
                {
                    "city_name": "西青",
                    "no": "101030500"
                },
                {
                    "city_name": "北辰",
                    "no": "101030600"
                },
                {
                    "city_name": "蓟县",
                    "no": "101031400"
                },
                {
                    "city_name": "汉沽",
                    "no": "101030800"
                },
                {
                    "city_name": "静海",
                    "no": "101030900"
                },
                {
                    "city_name": "津南",
                    "no": "101031000"
                },
                {
                    "city_name": "塘沽",
                    "no": "101031100"
                },
                {
                    "city_name": "大港",
                    "no": "101031200"
                },
                {
                    "city_name": "武清",
                    "no": "101030200"
                },
                {
                    "city_name": "宁河",
                    "no": "101030700"
                }
            ]
        },
        {
            "province": "上海",
            "city": [
                {
                    "city_name": "上海",
                    "no": "101020100"
                },
                {
                    "city_name": "宝山",
                    "no": "101020300"
                },
                {
                    "city_name": "嘉定",
                    "no": "101020500"
                },
                {
                    "city_name": "南汇",
                    "no": "101020600"
                },
                {
                    "city_name": "浦东",
                    "no": "101021300"
                },
                {
                    "city_name": "青浦",
                    "no": "101020800"
                },
                {
                    "city_name": "松江",
                    "no": "101020900"
                },
                {
                    "city_name": "奉贤",
                    "no": "101021000"
                },
                {
                    "city_name": "崇明",
                    "no": "101021100"
                },
                {
                    "city_name": "徐家汇",
                    "no": "101021200"
                },
                {
                    "city_name": "闵行",
                    "no": "101020200"
                },
                {
                    "city_name": "金山",
                    "no": "101020700"
                }
            ]
        },
        {
            "province": "河北",
            "city": [
                {
                    "city_name": "石家庄",
                    "no": "101090101"
                },
                {
                    "city_name": "张家口",
                    "no": "101090301"
                },
                {
                    "city_name": "承德",
                    "no": "101090402"
                },
                {
                    "city_name": "唐山",
                    "no": "101090501"
                },
                {
                    "city_name": "秦皇岛",
                    "no": "101091101"
                },
                {
                    "city_name": "沧州",
                    "no": "101090701"
                },
                {
                    "city_name": "衡水",
                    "no": "101090801"
                },
                {
                    "city_name": "邢台",
                    "no": "101090901"
                },
                {
                    "city_name": "邯郸",
                    "no": "101091001"
                },
                {
                    "city_name": "保定",
                    "no": "101090201"
                },
                {
                    "city_name": "廊坊",
                    "no": "101090601"
                }
            ]
        },
        {
            "province": "河南",
            "city": [
                {
                    "city_name": "郑州",
                    "no": "101180101"
                },
                {
                    "city_name": "新乡",
                    "no": "101180301"
                },
                {
                    "city_name": "许昌",
                    "no": "101180401"
                },
                {
                    "city_name": "平顶山",
                    "no": "101180501"
                },
                {
                    "city_name": "信阳",
                    "no": "101180601"
                },
                {
                    "city_name": "南阳",
                    "no": "101180701"
                },
                {
                    "city_name": "开封",
                    "no": "101180801"
                },
                {
                    "city_name": "洛阳",
                    "no": "101180901"
                },
                {
                    "city_name": "商丘",
                    "no": "101181001"
                },
                {
                    "city_name": "焦作",
                    "no": "101181101"
                },
                {
                    "city_name": "鹤壁",
                    "no": "101181201"
                },
                {
                    "city_name": "濮阳",
                    "no": "101181301"
                },
                {
                    "city_name": "周口",
                    "no": "101181401"
                },
                {
                    "city_name": "漯河",
                    "no": "101181501"
                },
                {
                    "city_name": "驻马店",
                    "no": "101181601"
                },
                {
                    "city_name": "三门峡",
                    "no": "101181701"
                },
                {
                    "city_name": "济源",
                    "no": "101181801"
                },
                {
                    "city_name": "安阳",
                    "no": "101180201"
                }
            ]
        },
        {
            "province": "安徽",
            "city": [
                {
                    "city_name": "合肥",
                    "no": "101220101"
                },
                {
                    "city_name": "芜湖",
                    "no": "101220301"
                },
                {
                    "city_name": "淮南",
                    "no": "101220401"
                },
                {
                    "city_name": "马鞍山",
                    "no": "101220501"
                },
                {
                    "city_name": "安庆",
                    "no": "101220601"
                },
                {
                    "city_name": "宿州",
                    "no": "101220701"
                },
                {
                    "city_name": "阜阳",
                    "no": "101220801"
                },
                {
                    "city_name": "亳州",
                    "no": "101220901"
                },
                {
                    "city_name": "黄山",
                    "no": "101221001"
                },
                {
                    "city_name": "滁州",
                    "no": "101221101"
                },
                {
                    "city_name": "淮北",
                    "no": "101221201"
                },
                {
                    "city_name": "铜陵",
                    "no": "101221301"
                },
                {
                    "city_name": "宣城",
                    "no": "101221401"
                },
                {
                    "city_name": "六安",
                    "no": "101221501"
                },
                {
                    "city_name": "巢湖",
                    "no": "101221601"
                },
                {
                    "city_name": "池州",
                    "no": "101221701"
                },
                {
                    "city_name": "蚌埠",
                    "no": "101220201"
                }
            ]
        },
        {
            "province": "浙江",
            "city": [
                {
                    "city_name": "杭州",
                    "no": "101210101"
                },
                {
                    "city_name": "舟山",
                    "no": "101211101"
                },
                {
                    "city_name": "湖州",
                    "no": "101210201"
                },
                {
                    "city_name": "嘉兴",
                    "no": "101210301"
                },
                {
                    "city_name": "金华",
                    "no": "101210901"
                },
                {
                    "city_name": "绍兴",
                    "no": "101210501"
                },
                {
                    "city_name": "台州",
                    "no": "101210601"
                },
                {
                    "city_name": "温州",
                    "no": "101210701"
                },
                {
                    "city_name": "丽水",
                    "no": "101210801"
                },
                {
                    "city_name": "衢州",
                    "no": "101211001"
                },
                {
                    "city_name": "宁波",
                    "no": "101210401"
                }
            ]
        },
        {
            "province": "重庆",
            "city": [
                {
                    "city_name": "重庆",
                    "no": "101040100"
                },
                {
                    "city_name": "合川",
                    "no": "101040300"
                },
                {
                    "city_name": "南川",
                    "no": "101040400"
                },
                {
                    "city_name": "江津",
                    "no": "101040500"
                },
                {
                    "city_name": "万盛",
                    "no": "101040600"
                },
                {
                    "city_name": "渝北",
                    "no": "101040700"
                },
                {
                    "city_name": "北碚",
                    "no": "101040800"
                },
                {
                    "city_name": "巴南",
                    "no": "101040900"
                },
                {
                    "city_name": "长寿",
                    "no": "101041000"
                },
                {
                    "city_name": "黔江",
                    "no": "101041100"
                },
                {
                    "city_name": "万州天城",
                    "no": "101041200"
                },
                {
                    "city_name": "万州龙宝",
                    "no": "101041300"
                },
                {
                    "city_name": "涪陵",
                    "no": "101041400"
                },
                {
                    "city_name": "开县",
                    "no": "101041500"
                },
                {
                    "city_name": "城口",
                    "no": "101041600"
                },
                {
                    "city_name": "云阳",
                    "no": "101041700"
                },
                {
                    "city_name": "巫溪",
                    "no": "101041800"
                },
                {
                    "city_name": "奉节",
                    "no": "101041900"
                },
                {
                    "city_name": "巫山",
                    "no": "101042000"
                },
                {
                    "city_name": "潼南",
                    "no": "101042100"
                },
                {
                    "city_name": "垫江",
                    "no": "101042200"
                },
                {
                    "city_name": "梁平",
                    "no": "101042300"
                },
                {
                    "city_name": "忠县",
                    "no": "101042400"
                },
                {
                    "city_name": "石柱",
                    "no": "101042500"
                },
                {
                    "city_name": "大足",
                    "no": "101042600"
                },
                {
                    "city_name": "荣昌",
                    "no": "101042700"
                },
                {
                    "city_name": "铜梁",
                    "no": "101042800"
                },
                {
                    "city_name": "璧山",
                    "no": "101042900"
                },
                {
                    "city_name": "丰都",
                    "no": "101043000"
                },
                {
                    "city_name": "武隆",
                    "no": "101043100"
                },
                {
                    "city_name": "彭水",
                    "no": "101043200"
                },
                {
                    "city_name": "綦江",
                    "no": "101043300"
                },
                {
                    "city_name": "酉阳",
                    "no": "101043400"
                },
                {
                    "city_name": "秀山",
                    "no": "101043600"
                },
                {
                    "city_name": "沙坪坝",
                    "no": "101043700"
                },
                {
                    "city_name": "永川",
                    "no": "101040200"
                }
            ]
        },
        {
            "province": "福建",
            "city": [
                {
                    "city_name": "福州",
                    "no": "101230101"
                },
                {
                    "city_name": "泉州",
                    "no": "101230501"
                },
                {
                    "city_name": "漳州",
                    "no": "101230601"
                },
                {
                    "city_name": "龙岩",
                    "no": "101230701"
                },
                {
                    "city_name": "晋江",
                    "no": "101230509"
                },
                {
                    "city_name": "南平",
                    "no": "101230901"
                },
                {
                    "city_name": "厦门",
                    "no": "101230201"
                },
                {
                    "city_name": "宁德",
                    "no": "101230301"
                },
                {
                    "city_name": "莆田",
                    "no": "101230401"
                },
                {
                    "city_name": "三明",
                    "no": "101230801"
                }
            ]
        },
        {
            "province": "甘肃",
            "city": [
                {
                    "city_name": "兰州",
                    "no": "101160101"
                },
                {
                    "city_name": "平凉",
                    "no": "101160301"
                },
                {
                    "city_name": "庆阳",
                    "no": "101160401"
                },
                {
                    "city_name": "武威",
                    "no": "101160501"
                },
                {
                    "city_name": "金昌",
                    "no": "101160601"
                },
                {
                    "city_name": "嘉峪关",
                    "no": "101161401"
                },
                {
                    "city_name": "酒泉",
                    "no": "101160801"
                },
                {
                    "city_name": "天水",
                    "no": "101160901"
                },
                {
                    "city_name": "武都",
                    "no": "101161001"
                },
                {
                    "city_name": "临夏",
                    "no": "101161101"
                },
                {
                    "city_name": "合作",
                    "no": "101161201"
                },
                {
                    "city_name": "白银",
                    "no": "101161301"
                },
                {
                    "city_name": "定西",
                    "no": "101160201"
                },
                {
                    "city_name": "张掖",
                    "no": "101160701"
                }
            ]
        },
        {
            "province": "广东",
            "city": [
                {
                    "city_name": "广州",
                    "no": "101280101"
                },
                {
                    "city_name": "惠州",
                    "no": "101280301"
                },
                {
                    "city_name": "梅州",
                    "no": "101280401"
                },
                {
                    "city_name": "汕头",
                    "no": "101280501"
                },
                {
                    "city_name": "深圳",
                    "no": "101280601"
                },
                {
                    "city_name": "珠海",
                    "no": "101280701"
                },
                {
                    "city_name": "佛山",
                    "no": "101280800"
                },
                {
                    "city_name": "肇庆",
                    "no": "101280901"
                },
                {
                    "city_name": "湛江",
                    "no": "101281001"
                },
                {
                    "city_name": "江门",
                    "no": "101281101"
                },
                {
                    "city_name": "河源",
                    "no": "101281201"
                },
                {
                    "city_name": "清远",
                    "no": "101281301"
                },
                {
                    "city_name": "云浮",
                    "no": "101281401"
                },
                {
                    "city_name": "潮州",
                    "no": "101281501"
                },
                {
                    "city_name": "东莞",
                    "no": "101281601"
                },
                {
                    "city_name": "中山",
                    "no": "101281701"
                },
                {
                    "city_name": "阳江",
                    "no": "101281801"
                },
                {
                    "city_name": "揭阳",
                    "no": "101281901"
                },
                {
                    "city_name": "茂名",
                    "no": "101282001"
                },
                {
                    "city_name": "汕尾",
                    "no": "101282101"
                },
                {
                    "city_name": "韶关",
                    "no": "101280201"
                }
            ]
        },
        {
            "province": "广西",
            "city": [
                {
                    "city_name": "南宁",
                    "no": "101300101"
                },
                {
                    "city_name": "柳州",
                    "no": "101300301"
                },
                {
                    "city_name": "来宾",
                    "no": "101300401"
                },
                {
                    "city_name": "桂林",
                    "no": "101300501"
                },
                {
                    "city_name": "梧州",
                    "no": "101300601"
                },
                {
                    "city_name": "防城港",
                    "no": "101301401"
                },
                {
                    "city_name": "贵港",
                    "no": "101300801"
                },
                {
                    "city_name": "玉林",
                    "no": "101300901"
                },
                {
                    "city_name": "百色",
                    "no": "101301001"
                },
                {
                    "city_name": "钦州",
                    "no": "101301101"
                },
                {
                    "city_name": "河池",
                    "no": "101301201"
                },
                {
                    "city_name": "北海",
                    "no": "101301301"
                },
                {
                    "city_name": "崇左",
                    "no": "101300201"
                },
                {
                    "city_name": "贺州",
                    "no": "101300701"
                }
            ]
        },
        {
            "province": "贵州",
            "city": [
                {
                    "city_name": "贵阳",
                    "no": "101260101"
                },
                {
                    "city_name": "安顺",
                    "no": "101260301"
                },
                {
                    "city_name": "都匀",
                    "no": "101260401"
                },
                {
                    "city_name": "兴义",
                    "no": "101260906"
                },
                {
                    "city_name": "铜仁",
                    "no": "101260601"
                },
                {
                    "city_name": "毕节",
                    "no": "101260701"
                },
                {
                    "city_name": "六盘水",
                    "no": "101260801"
                },
                {
                    "city_name": "遵义",
                    "no": "101260201"
                },
                {
                    "city_name": "凯里",
                    "no": "101260501"
                }
            ]
        },
        {
            "province": "云南",
            "city": [
                {
                    "city_name": "昆明",
                    "no": "101290101"
                },
                {
                    "city_name": "红河",
                    "no": "101290301"
                },
                {
                    "city_name": "文山",
                    "no": "101290601"
                },
                {
                    "city_name": "玉溪",
                    "no": "101290701"
                },
                {
                    "city_name": "楚雄",
                    "no": "101290801"
                },
                {
                    "city_name": "普洱",
                    "no": "101290901"
                },
                {
                    "city_name": "昭通",
                    "no": "101291001"
                },
                {
                    "city_name": "临沧",
                    "no": "101291101"
                },
                {
                    "city_name": "怒江",
                    "no": "101291201"
                },
                {
                    "city_name": "香格里拉",
                    "no": "101291301"
                },
                {
                    "city_name": "丽江",
                    "no": "101291401"
                },
                {
                    "city_name": "德宏",
                    "no": "101291501"
                },
                {
                    "city_name": "景洪",
                    "no": "101291601"
                },
                {
                    "city_name": "大理",
                    "no": "101290201"
                },
                {
                    "city_name": "曲靖",
                    "no": "101290401"
                },
                {
                    "city_name": "保山",
                    "no": "101290501"
                }
            ]
        },
        {
            "province": "内蒙古",
            "city": [
                {
                    "city_name": "呼和浩特",
                    "no": "101080101"
                },
                {
                    "city_name": "乌海",
                    "no": "101080301"
                },
                {
                    "city_name": "集宁",
                    "no": "101080401"
                },
                {
                    "city_name": "通辽",
                    "no": "101080501"
                },
                {
                    "city_name": "阿拉善左旗",
                    "no": "101081201"
                },
                {
                    "city_name": "鄂尔多斯",
                    "no": "101080701"
                },
                {
                    "city_name": "临河",
                    "no": "101080801"
                },
                {
                    "city_name": "锡林浩特",
                    "no": "101080901"
                },
                {
                    "city_name": "呼伦贝尔",
                    "no": "101081000"
                },
                {
                    "city_name": "乌兰浩特",
                    "no": "101081101"
                },
                {
                    "city_name": "包头",
                    "no": "101080201"
                },
                {
                    "city_name": "赤峰",
                    "no": "101080601"
                }
            ]
        },
        {
            "province": "江西",
            "city": [
                {
                    "city_name": "南昌",
                    "no": "101240101"
                },
                {
                    "city_name": "上饶",
                    "no": "101240301"
                },
                {
                    "city_name": "抚州",
                    "no": "101240401"
                },
                {
                    "city_name": "宜春",
                    "no": "101240501"
                },
                {
                    "city_name": "鹰潭",
                    "no": "101241101"
                },
                {
                    "city_name": "赣州",
                    "no": "101240701"
                },
                {
                    "city_name": "景德镇",
                    "no": "101240801"
                },
                {
                    "city_name": "萍乡",
                    "no": "101240901"
                },
                {
                    "city_name": "新余",
                    "no": "101241001"
                },
                {
                    "city_name": "九江",
                    "no": "101240201"
                },
                {
                    "city_name": "吉安",
                    "no": "101240601"
                }
            ]
        },
        {
            "province": "湖北",
            "city": [
                {
                    "city_name": "武汉",
                    "no": "101200101"
                },
                {
                    "city_name": "黄冈",
                    "no": "101200501"
                },
                {
                    "city_name": "荆州",
                    "no": "101200801"
                },
                {
                    "city_name": "宜昌",
                    "no": "101200901"
                },
                {
                    "city_name": "恩施",
                    "no": "101201001"
                },
                {
                    "city_name": "十堰",
                    "no": "101201101"
                },
                {
                    "city_name": "神农架",
                    "no": "101201201"
                },
                {
                    "city_name": "随州",
                    "no": "101201301"
                },
                {
                    "city_name": "荆门",
                    "no": "101201401"
                },
                {
                    "city_name": "天门",
                    "no": "101201501"
                },
                {
                    "city_name": "仙桃",
                    "no": "101201601"
                },
                {
                    "city_name": "潜江",
                    "no": "101201701"
                },
                {
                    "city_name": "襄樊",
                    "no": "101200201"
                },
                {
                    "city_name": "鄂州",
                    "no": "101200301"
                },
                {
                    "city_name": "孝感",
                    "no": "101200401"
                },
                {
                    "city_name": "黄石",
                    "no": "101200601"
                },
                {
                    "city_name": "咸宁",
                    "no": "101200701"
                }
            ]
        },
        {
            "province": "四川",
            "city": [
                {
                    "city_name": "成都",
                    "no": "101270101"
                },
                {
                    "city_name": "自贡",
                    "no": "101270301"
                },
                {
                    "city_name": "绵阳",
                    "no": "101270401"
                },
                {
                    "city_name": "南充",
                    "no": "101270501"
                },
                {
                    "city_name": "达州",
                    "no": "101270601"
                },
                {
                    "city_name": "遂宁",
                    "no": "101270701"
                },
                {
                    "city_name": "广安",
                    "no": "101270801"
                },
                {
                    "city_name": "巴中",
                    "no": "101270901"
                },
                {
                    "city_name": "泸州",
                    "no": "101271001"
                },
                {
                    "city_name": "宜宾",
                    "no": "101271101"
                },
                {
                    "city_name": "内江",
                    "no": "101271201"
                },
                {
                    "city_name": "资阳",
                    "no": "101271301"
                },
                {
                    "city_name": "乐山",
                    "no": "101271401"
                },
                {
                    "city_name": "眉山",
                    "no": "101271501"
                },
                {
                    "city_name": "凉山",
                    "no": "101271601"
                },
                {
                    "city_name": "雅安",
                    "no": "101271701"
                },
                {
                    "city_name": "甘孜",
                    "no": "101271801"
                },
                {
                    "city_name": "阿坝",
                    "no": "101271901"
                },
                {
                    "city_name": "德阳",
                    "no": "101272001"
                },
                {
                    "city_name": "广元",
                    "no": "101272101"
                },
                {
                    "city_name": "攀枝花",
                    "no": "101270201"
                }
            ]
        },
        {
            "province": "宁夏",
            "city": [
                {
                    "city_name": "银川",
                    "no": "101170101"
                },
                {
                    "city_name": "中卫",
                    "no": "101170501"
                },
                {
                    "city_name": "固原",
                    "no": "101170401"
                },
                {
                    "city_name": "石嘴山",
                    "no": "101170201"
                },
                {
                    "city_name": "吴忠",
                    "no": "101170301"
                }
            ]
        },
        {
            "province": "青海",
            "city": [
                {
                    "city_name": "西宁",
                    "no": "101150101"
                },
                {
                    "city_name": "黄南",
                    "no": "101150301"
                },
                {
                    "city_name": "海北",
                    "no": "101150801"
                },
                {
                    "city_name": "果洛",
                    "no": "101150501"
                },
                {
                    "city_name": "玉树",
                    "no": "101150601"
                },
                {
                    "city_name": "海西",
                    "no": "101150701"
                },
                {
                    "city_name": "海东",
                    "no": "101150201"
                },
                {
                    "city_name": "海南",
                    "no": "101150401"
                }
            ]
        },
        {
            "province": "山东",
            "city": [
                {
                    "city_name": "济南",
                    "no": "101120101"
                },
                {
                    "city_name": "潍坊",
                    "no": "101120601"
                },
                {
                    "city_name": "临沂",
                    "no": "101120901"
                },
                {
                    "city_name": "菏泽",
                    "no": "101121001"
                },
                {
                    "city_name": "滨州",
                    "no": "101121101"
                },
                {
                    "city_name": "东营",
                    "no": "101121201"
                },
                {
                    "city_name": "威海",
                    "no": "101121301"
                },
                {
                    "city_name": "枣庄",
                    "no": "101121401"
                },
                {
                    "city_name": "日照",
                    "no": "101121501"
                },
                {
                    "city_name": "莱芜",
                    "no": "101121601"
                },
                {
                    "city_name": "聊城",
                    "no": "101121701"
                },
                {
                    "city_name": "青岛",
                    "no": "101120201"
                },
                {
                    "city_name": "淄博",
                    "no": "101120301"
                },
                {
                    "city_name": "德州",
                    "no": "101120401"
                },
                {
                    "city_name": "烟台",
                    "no": "101120501"
                },
                {
                    "city_name": "济宁",
                    "no": "101120701"
                },
                {
                    "city_name": "泰安",
                    "no": "101120801"
                }
            ]
        },
        {
            "province": "陕西",
            "city": [
                {
                    "city_name": "西安",
                    "no": "101110101"
                },
                {
                    "city_name": "延安",
                    "no": "101110300"
                },
                {
                    "city_name": "榆林",
                    "no": "101110401"
                },
                {
                    "city_name": "铜川",
                    "no": "101111001"
                },
                {
                    "city_name": "商洛",
                    "no": "101110601"
                },
                {
                    "city_name": "安康",
                    "no": "101110701"
                },
                {
                    "city_name": "汉中",
                    "no": "101110801"
                },
                {
                    "city_name": "宝鸡",
                    "no": "101110901"
                },
                {
                    "city_name": "咸阳",
                    "no": "101110200"
                },
                {
                    "city_name": "渭南",
                    "no": "101110501"
                }
            ]
        },
        {
            "province": "山西",
            "city": [
                {
                    "city_name": "太原",
                    "no": "101100101"
                },
                {
                    "city_name": "临汾",
                    "no": "101100701"
                },
                {
                    "city_name": "运城",
                    "no": "101100801"
                },
                {
                    "city_name": "朔州",
                    "no": "101100901"
                },
                {
                    "city_name": "忻州",
                    "no": "101101001"
                },
                {
                    "city_name": "长治",
                    "no": "101100501"
                },
                {
                    "city_name": "大同",
                    "no": "101100201"
                },
                {
                    "city_name": "阳泉",
                    "no": "101100301"
                },
                {
                    "city_name": "晋中",
                    "no": "101100401"
                },
                {
                    "city_name": "晋城",
                    "no": "101100601"
                },
                {
                    "city_name": "吕梁",
                    "no": "101101100"
                }
            ]
        },
        {
            "province": "新疆",
            "city": [
                {
                    "city_name": "乌鲁木齐",
                    "no": "101130101"
                },
                {
                    "city_name": "石河子",
                    "no": "101130301"
                },
                {
                    "city_name": "昌吉",
                    "no": "101130401"
                },
                {
                    "city_name": "吐鲁番",
                    "no": "101130501"
                },
                {
                    "city_name": "库尔勒",
                    "no": "101130601"
                },
                {
                    "city_name": "阿拉尔",
                    "no": "101130701"
                },
                {
                    "city_name": "阿克苏",
                    "no": "101130801"
                },
                {
                    "city_name": "喀什",
                    "no": "101130901"
                },
                {
                    "city_name": "伊宁",
                    "no": "101131001"
                },
                {
                    "city_name": "塔城",
                    "no": "101131101"
                },
                {
                    "city_name": "哈密",
                    "no": "101131201"
                },
                {
                    "city_name": "和田",
                    "no": "101131301"
                },
                {
                    "city_name": "阿勒泰",
                    "no": "101131401"
                },
                {
                    "city_name": "阿图什",
                    "no": "101131501"
                },
                {
                    "city_name": "博乐",
                    "no": "101131601"
                },
                {
                    "city_name": "克拉玛依",
                    "no": "101130201"
                }
            ]
        },
        {
            "province": "西藏",
            "city": [
                {
                    "city_name": "拉萨",
                    "no": "101140101"
                },
                {
                    "city_name": "山南",
                    "no": "101140301"
                },
                {
                    "city_name": "阿里",
                    "no": "101140701"
                },
                {
                    "city_name": "昌都",
                    "no": "101140501"
                },
                {
                    "city_name": "那曲",
                    "no": "101140601"
                },
                {
                    "city_name": "日喀则",
                    "no": "101140201"
                },
                {
                    "city_name": "林芝",
                    "no": "101140401"
                }
            ]
        },
        {
            "province": "台湾",
            "city": [
                {
                    "city_name": "台北县",
                    "no": "101340101"
                },
                {
                    "city_name": "高雄",
                    "no": "101340201"
                },
                {
                    "city_name": "台中",
                    "no": "101340401"
                }
            ]
        },
        {
            "province": "海南",
            "city": [
                {
                    "city_name": "海口",
                    "no": "101310101"
                },
                {
                    "city_name": "三亚",
                    "no": "101310201"
                },
                {
                    "city_name": "东方",
                    "no": "101310202"
                },
                {
                    "city_name": "临高",
                    "no": "101310203"
                },
                {
                    "city_name": "澄迈",
                    "no": "101310204"
                },
                {
                    "city_name": "儋州",
                    "no": "101310205"
                },
                {
                    "city_name": "昌江",
                    "no": "101310206"
                },
                {
                    "city_name": "白沙",
                    "no": "101310207"
                },
                {
                    "city_name": "琼中",
                    "no": "101310208"
                },
                {
                    "city_name": "定安",
                    "no": "101310209"
                },
                {
                    "city_name": "屯昌",
                    "no": "101310210"
                },
                {
                    "city_name": "琼海",
                    "no": "101310211"
                },
                {
                    "city_name": "文昌",
                    "no": "101310212"
                },
                {
                    "city_name": "保亭",
                    "no": "101310214"
                },
                {
                    "city_name": "万宁",
                    "no": "101310215"
                },
                {
                    "city_name": "陵水",
                    "no": "101310216"
                },
                {
                    "city_name": "西沙",
                    "no": "101310217"
                },
                {
                    "city_name": "南沙岛",
                    "no": "101310220"
                },
                {
                    "city_name": "乐东",
                    "no": "101310221"
                },
                {
                    "city_name": "五指山",
                    "no": "101310222"
                },
                {
                    "city_name": "琼山",
                    "no": "101310102"
                }
            ]
        },
        {
            "province": "湖南",
            "city": [
                {
                    "city_name": "长沙",
                    "no": "101250101"
                },
                {
                    "city_name": "株洲",
                    "no": "101250301"
                },
                {
                    "city_name": "衡阳",
                    "no": "101250401"
                },
                {
                    "city_name": "郴州",
                    "no": "101250501"
                },
                {
                    "city_name": "常德",
                    "no": "101250601"
                },
                {
                    "city_name": "益阳",
                    "no": "101250700"
                },
                {
                    "city_name": "娄底",
                    "no": "101250801"
                },
                {
                    "city_name": "邵阳",
                    "no": "101250901"
                },
                {
                    "city_name": "岳阳",
                    "no": "101251001"
                },
                {
                    "city_name": "张家界",
                    "no": "101251101"
                },
                {
                    "city_name": "怀化",
                    "no": "101251201"
                },
                {
                    "city_name": "黔阳",
                    "no": "101251301"
                },
                {
                    "city_name": "永州",
                    "no": "101251401"
                },
                {
                    "city_name": "吉首",
                    "no": "101251501"
                },
                {
                    "city_name": "湘潭",
                    "no": "101250201"
                }
            ]
        },
        {
            "province": "江苏",
            "city": [
                {
                    "city_name": "南京",
                    "no": "101190101"
                },
                {
                    "city_name": "镇江",
                    "no": "101190301"
                },
                {
                    "city_name": "苏州",
                    "no": "101190401"
                },
                {
                    "city_name": "南通",
                    "no": "101190501"
                },
                {
                    "city_name": "扬州",
                    "no": "101190601"
                },
                {
                    "city_name": "宿迁",
                    "no": "101191301"
                },
                {
                    "city_name": "徐州",
                    "no": "101190801"
                },
                {
                    "city_name": "淮安",
                    "no": "101190901"
                },
                {
                    "city_name": "连云港",
                    "no": "101191001"
                },
                {
                    "city_name": "常州",
                    "no": "101191101"
                },
                {
                    "city_name": "泰州",
                    "no": "101191201"
                },
                {
                    "city_name": "无锡",
                    "no": "101190201"
                },
                {
                    "city_name": "盐城",
                    "no": "101190701"
                }
            ]
        },
        {
            "province": "黑龙江",
            "city": [
                {
                    "city_name": "哈尔滨",
                    "no": "101050101"
                },
                {
                    "city_name": "牡丹江",
                    "no": "101050301"
                },
                {
                    "city_name": "佳木斯",
                    "no": "101050401"
                },
                {
                    "city_name": "绥化",
                    "no": "101050501"
                },
                {
                    "city_name": "黑河",
                    "no": "101050601"
                },
                {
                    "city_name": "双鸭山",
                    "no": "101051301"
                },
                {
                    "city_name": "伊春",
                    "no": "101050801"
                },
                {
                    "city_name": "大庆",
                    "no": "101050901"
                },
                {
                    "city_name": "七台河",
                    "no": "101051002"
                },
                {
                    "city_name": "鸡西",
                    "no": "101051101"
                },
                {
                    "city_name": "鹤岗",
                    "no": "101051201"
                },
                {
                    "city_name": "齐齐哈尔",
                    "no": "101050201"
                },
                {
                    "city_name": "大兴安岭",
                    "no": "101050701"
                }
            ]
        },
        {
            "province": "吉林",
            "city": [
                {
                    "city_name": "长春",
                    "no": "101060101"
                },
                {
                    "city_name": "延吉",
                    "no": "101060301"
                },
                {
                    "city_name": "四平",
                    "no": "101060401"
                },
                {
                    "city_name": "白山",
                    "no": "101060901"
                },
                {
                    "city_name": "白城",
                    "no": "101060601"
                },
                {
                    "city_name": "辽源",
                    "no": "101060701"
                },
                {
                    "city_name": "松原",
                    "no": "101060801"
                },
                {
                    "city_name": "吉林",
                    "no": "101060201"
                },
                {
                    "city_name": "通化",
                    "no": "101060501"
                }
            ]
        },
        {
            "province": "辽宁",
            "city": [
                {
                    "city_name": "沈阳",
                    "no": "101070101"
                },
                {
                    "city_name": "鞍山",
                    "no": "101070301"
                },
                {
                    "city_name": "抚顺",
                    "no": "101070401"
                },
                {
                    "city_name": "本溪",
                    "no": "101070501"
                },
                {
                    "city_name": "丹东",
                    "no": "101070601"
                },
                {
                    "city_name": "葫芦岛",
                    "no": "101071401"
                },
                {
                    "city_name": "营口",
                    "no": "101070801"
                },
                {
                    "city_name": "阜新",
                    "no": "101070901"
                },
                {
                    "city_name": "辽阳",
                    "no": "101071001"
                },
                {
                    "city_name": "铁岭",
                    "no": "101071101"
                },
                {
                    "city_name": "朝阳",
                    "no": "101071201"
                },
                {
                    "city_name": "盘锦",
                    "no": "101071301"
                },
                {
                    "city_name": "大连",
                    "no": "101070201"
                },
                {
                    "city_name": "锦州",
                    "no": "101070701"
                }
            ]
        }
    ]
}